hcli_hak11/__init__.py
hcli_hak11/__main__.py
hcli_hak11/config.py
hcli_hak11/hutils.py
hcli_hak11/package.py
hcli_hak11/__pycache__/__init__.cpython-311.pyc
hcli_hak11/__pycache__/config.cpython-311.pyc
hcli_hak11/__pycache__/package.cpython-311.pyc
hcli_hak11/cli/__init__.py
hcli_hak11/cli/cli.py
hcli_hak11/cli/logger.py
hcli_hak11/cli/service.py
hcli_hak11/cli/template.json
hcli_hak11/cli/relay/__init__.py
hcli_hak11/cli/relay/relay.py
hcli_hak11/data/hcli_hak11.1
hcli_hak11-0.1.2.dist-info/LICENSE.txt
hcli_hak11-0.1.2.dist-info/METADATA
hcli_hak11-0.1.2.dist-info/WHEEL
hcli_hak11-0.1.2.dist-info/entry_points.txt
hcli_hak11-0.1.2.dist-info/top_level.txt
hcli_hak11-0.1.2.dist-info/RECORD
