Metadata-Version: 2.1
Name: hcli_hak11
Version: 0.1.2
Summary: HCLI hak11 is a python package wrapper that contains an HCLI sample application (hak11); hak11 is intended to run on a rapsberry pi setup to trigger relays via GPIO. 12 GPIO triggered relays are intended to be setup to interact with a Linear AK-11 keypad to enable remote administration.
Author-email: Jeff Michaud <cometaj2@comcast.net>
License: MIT
Project-URL: Homepage, https://github.com/cometaj2/hcli_hak11
Keywords: cli,client,server,connector,hypermedia,rest,generic,development
Classifier: Development Status :: 2 - Pre-Alpha
Classifier: Intended Audience :: Developers
Classifier: Topic :: Software Development
Classifier: License :: OSI Approved :: MIT License
Classifier: Programming Language :: Python :: 3.9
Classifier: Programming Language :: Python :: 3.10
Classifier: Programming Language :: Python :: 3.11
Classifier: Programming Language :: Python :: 3.12
License-File: LICENSE.txt
Requires-Dist: gpiozero==2.0.1
